maybach_requests/__init__.py
maybach_requests-1.0.1.dist-info/METADATA
maybach_requests-1.0.1.dist-info/WHEEL
maybach_requests-1.0.1.dist-info/top_level.txt
maybach_requests-1.0.1.dist-info/RECORD
