Metadata-Version: 2.1
Name: maybach-requests
Version: 1.0.1
Summary: UNKNOWN
Home-page: https://gitlab.xiguacity.cn/fee/python/maybach-requests
Author: cuvee
Author-email: cuizaiyong@xigua.club
License: MIT
Platform: UNKNOWN
